{
  "pageViews": {
    "/": 7,
    "/about": 2,
    "/services": 0,
    "/products": 1,
    "/contact": 0,
    "/admin/analytics": 1,
    "/privacy": 4
  },
  "events": {
    "consultation_booked": 0
  },
  "logs": [
    {
      "timestamp": "2026-07-16T03:47:04.805Z",
      "action": "Page View",
      "details": "/"
    },
    {
      "timestamp": "2026-07-16T03:47:16.870Z",
      "action": "Page View",
      "details": "/admin/analytics"
    },
    {
      "timestamp": "2026-07-16T04:05:33.419Z",
      "action": "Page View",
      "details": "/"
    },
    {
      "timestamp": "2026-07-16T04:49:00.818Z",
      "action": "Page View",
      "details": "/products"
    },
    {
      "timestamp": "2026-07-16T04:49:13.498Z",
      "action": "Page View",
      "details": "/"
    },
    {
      "timestamp": "2026-07-16T04:52:46.688Z",
      "action": "Page View",
      "details": "/"
    },
    {
      "timestamp": "2026-07-16T08:18:39.503Z",
      "action": "Page View",
      "details": "/privacy"
    },
    {
      "timestamp": "2026-07-16T08:20:45.155Z",
      "action": "Page View",
      "details": "/privacy"
    },
    {
      "timestamp": "2026-07-16T08:27:59.777Z",
      "action": "Page View",
      "details": "/privacy"
    },
    {
      "timestamp": "2026-07-16T08:28:13.359Z",
      "action": "Page View",
      "details": "/privacy"
    },
    {
      "timestamp": "2026-07-16T08:28:16.684Z",
      "action": "Page View",
      "details": "/"
    },
    {
      "timestamp": "2026-07-16T08:28:21.950Z",
      "action": "Page View",
      "details": "/about"
    },
    {
      "timestamp": "2026-07-16T08:28:27.939Z",
      "action": "Page View",
      "details": "/about"
    },
    {
      "timestamp": "2026-07-16T08:28:38.079Z",
      "action": "Page View",
      "details": "/"
    },
    {
      "timestamp": "2026-07-16T08:45:34.363Z",
      "action": "Page View",
      "details": "/"
    }
  ]
}